{
  "group_0": [
    {
      "alpha": 1000.0,
      "component": "strong_oof_ridge_stack",
      "feature": "tabm_prediction",
      "fit_rows": 0,
      "fold": "rw_01",
      "value": 0.0
    },
    {
      "alpha": 1000.0,
      "component": "strong_oof_ridge_stack",
      "feature": "tree_prediction",
      "fit_rows": 0,
      "fold": "rw_01",
      "value": 0.0
    },
    {
      "alpha": 1000.0,
      "component": "strong_oof_ridge_stack",
      "feature": "xgboost_prediction",
      "fit_rows": 0,
      "fold": "rw_01",
      "value": 0.0
    },
    {
      "alpha": 1000.0,
      "component": "strong_oof_ridge_stack",
      "feature": "lightgbm_prediction",
      "fit_rows": 0,
      "fold": "rw_01",
      "value": 0.0
    },
    {
      "alpha": 1000.0,
      "component": "strong_oof_ridge_stack",
      "feature": "ridge_calibrated_prediction",
      "fit_rows": 0,
      "fold": "rw_01",
      "value": 0.0
    },
    {
      "alpha": 1000.0,
      "component": "strong_oof_ridge_stack",
      "feature": "baseline_prediction",
      "fit_rows": 0,
      "fold": "rw_01",
      "value": 0.0
    },
    {
      "alpha": 1000.0,
      "component": "strong_oof_ridge_stack",
      "feature": "conservative_rls_prediction",
      "fit_rows": 0,
      "fold": "rw_01",
      "value": 1.0
    },
    {
      "alpha": 1000.0,
      "component": "strong_oof_ridge_stack",
      "feature": "aggressive_rls_prediction",
      "fit_rows": 0,
      "fold": "rw_01",
      "value": 0.0
    },
    {
      "alpha": 1000.0,
      "component": "strong_oof_ridge_stack",
      "feature": "tabm_s23_aux8_tabm_prediction",
      "fit_rows": 0,
      "fold": "rw_01",
      "value": 0.0
    },
    {
      "alpha": 1000.0,
      "component": "strong_oof_ridge_stack",
      "feature": "tabm_s17_tabm_prediction",
      "fit_rows": 0,
      "fold": "rw_01",
      "value": 0.0
    },
    {
      "alpha": 1000.0,
      "component": "strong_oof_ridge_stack",
      "feature": "gateway_risk_conservative_rls_abs_pred_s25_prediction",
      "fit_rows": 0,
      "fold": "rw_01",
      "value": 0.0
    },
    {
      "alpha": 1000.0,
      "component": "strong_oof_ridge_stack",
      "feature": "gateway_risk_conservative_rls_abs_pred_s100_prediction",
      "fit_rows": 0,
      "fold": "rw_01",
      "value": 0.0
    },
    {
      "alpha": 1000.0,
      "component": "strong_oof_ridge_stack",
      "feature": "gateway_risk_aggressive_rls_abs_pred_s25_prediction",
      "fit_rows": 0,
      "fold": "rw_01",
      "value": 0.0
    },
    {
      "alpha": 1000.0,
      "component": "strong_oof_ridge_stack",
      "feature": "gateway_risk_aggressive_rls_abs_pred_s100_prediction",
      "fit_rows": 0,
      "fold": "rw_01",
      "value": 0.0
    },
    {
      "alpha": 1000.0,
      "component": "strong_oof_ridge_stack",
      "feature": "tabm_prediction",
      "fit_rows": 431728,
      "fold": "rw_02",
      "value": -0.016524952351940386
    },
    {
      "alpha": 1000.0,
      "component": "strong_oof_ridge_stack",
      "feature": "tree_prediction",
      "fit_rows": 431728,
      "fold": "rw_02",
      "value": 0.13843356975915166
    },
    {
      "alpha": 1000.0,
      "component": "strong_oof_ridge_stack",
      "feature": "xgboost_prediction",
      "fit_rows": 431728,
      "fold": "rw_02",
      "value": 0.1865363287615866
    },
    {
      "alpha": 1000.0,
      "component": "strong_oof_ridge_stack",
      "feature": "lightgbm_prediction",
      "fit_rows": 431728,
      "fold": "rw_02",
      "value": 0.14807761569277078
    },
    {
      "alpha": 1000.0,
      "component": "strong_oof_ridge_stack",
      "feature": "ridge_calibrated_prediction",
      "fit_rows": 431728,
      "fold": "rw_02",
      "value": 0.018377607252672016
    },
    {
      "alpha": 1000.0,
      "component": "strong_oof_ridge_stack",
      "feature": "baseline_prediction",
      "fit_rows": 431728,
      "fold": "rw_02",
      "value": -0.016524952351940396
    },
    {
      "alpha": 1000.0,
      "component": "strong_oof_ridge_stack",
      "feature": "conservative_rls_prediction",
      "fit_rows": 431728,
      "fold": "rw_02",
      "value": 0.14996014878926583
    },
    {
      "alpha": 1000.0,
      "component": "strong_oof_ridge_stack",
      "feature": "aggressive_rls_prediction",
      "fit_rows": 431728,
      "fold": "rw_02",
      "value": 0.04623074081140578
    },
    {
      "alpha": 1000.0,
      "component": "strong_oof_ridge_stack",
      "feature": "tabm_s23_aux8_tabm_prediction",
      "fit_rows": 431728,
      "fold": "rw_02",
      "value": 0.25660948719969257
    },
    {
      "alpha": 1000.0,
      "component": "strong_oof_ridge_stack",
      "feature": "tabm_s17_tabm_prediction",
      "fit_rows": 431728,
      "fold": "rw_02",
      "value": 0.07789429406451082
    },
    {
      "alpha": 1000.0,
      "component": "strong_oof_ridge_stack",
      "feature": "gateway_risk_conservative_rls_abs_pred_s25_prediction",
      "fit_rows": 431728,
      "fold": "rw_02",
      "value": 0.14081831056294156
    },
    {
      "alpha": 1000.0,
      "component": "strong_oof_ridge_stack",
      "feature": "gateway_risk_conservative_rls_abs_pred_s100_prediction",
      "fit_rows": 431728,
      "fold": "rw_02",
      "value": 0.08933473951810299
    },
    {
      "alpha": 1000.0,
      "component": "strong_oof_ridge_stack",
      "feature": "gateway_risk_aggressive_rls_abs_pred_s25_prediction",
      "fit_rows": 431728,
      "fold": "rw_02",
      "value": 0.06864307731102513
    },
    {
      "alpha": 1000.0,
      "component": "strong_oof_ridge_stack",
      "feature": "gateway_risk_aggressive_rls_abs_pred_s100_prediction",
      "fit_rows": 431728,
      "fold": "rw_02",
      "value": 0.06350091481498416
    },
    {
      "alpha": 1000.0,
      "component": "strong_oof_ridge_stack",
      "feature": "tabm_prediction",
      "fit_rows": 868296,
      "fold": "rw_03",
      "value": 0.03549475287327235
    },
    {
      "alpha": 1000.0,
      "component": "strong_oof_ridge_stack",
      "feature": "tree_prediction",
      "fit_rows": 868296,
      "fold": "rw_03",
      "value": 0.15224472095425245
    },
    {
      "alpha": 1000.0,
      "component": "strong_oof_ridge_stack",
      "feature": "xgboost_prediction",
      "fit_rows": 868296,
      "fold": "rw_03",
      "value": 0.21151709522747517
    },
    {
      "alpha": 1000.0,
      "component": "strong_oof_ridge_stack",
      "feature": "lightgbm_prediction",
      "fit_rows": 868296,
      "fold": "rw_03",
      "value": 0.13840915117876462
    },
    {
      "alpha": 1000.0,
      "component": "strong_oof_ridge_stack",
      "feature": "ridge_calibrated_prediction",
      "fit_rows": 868296,
      "fold": "rw_03",
      "value": 0.025551648642803876
    },
    {
      "alpha": 1000.0,
      "component": "strong_oof_ridge_stack",
      "feature": "baseline_prediction",
      "fit_rows": 868296,
      "fold": "rw_03",
      "value": -0.052471811401065604
    },
    {
      "alpha": 1000.0,
      "component": "strong_oof_ridge_stack",
      "feature": "conservative_rls_prediction",
      "fit_rows": 868296,
      "fold": "rw_03",
      "value": 0.12182228707613081
    },
    {
      "alpha": 1000.0,
      "component": "strong_oof_ridge_stack",
      "feature": "aggressive_rls_prediction",
      "fit_rows": 868296,
      "fold": "rw_03",
      "value": 0.037642545285227785
    },
    {
      "alpha": 1000.0,
      "component": "strong_oof_ridge_stack",
      "feature": "tabm_s23_aux8_tabm_prediction",
      "fit_rows": 868296,
      "fold": "rw_03",
      "value": 0.19217452070257404
    },
    {
      "alpha": 1000.0,
      "component": "strong_oof_ridge_stack",
      "feature": "tabm_s17_tabm_prediction",
      "fit_rows": 868296,
      "fold": "rw_03",
      "value": 0.1754509624658413
    },
    {
      "alpha": 1000.0,
      "component": "strong_oof_ridge_stack",
      "feature": "gateway_risk_conservative_rls_abs_pred_s25_prediction",
      "fit_rows": 868296,
      "fold": "rw_03",
      "value": 0.16173276116970764
    },
    {
      "alpha": 1000.0,
      "component": "strong_oof_ridge_stack",
      "feature": "gateway_risk_conservative_rls_abs_pred_s100_prediction",
      "fit_rows": 868296,
      "fold": "rw_03",
      "value": 0.1165780890527337
    },
    {
      "alpha": 1000.0,
      "component": "strong_oof_ridge_stack",
      "feature": "gateway_risk_aggressive_rls_abs_pred_s25_prediction",
      "fit_rows": 868296,
      "fold": "rw_03",
      "value": 0.06959799475495852
    },
    {
      "alpha": 1000.0,
      "component": "strong_oof_ridge_stack",
      "feature": "gateway_risk_aggressive_rls_abs_pred_s100_prediction",
      "fit_rows": 868296,
      "fold": "rw_03",
      "value": 0.06630039769262995
    },
    {
      "alpha": 1000.0,
      "component": "strong_oof_ridge_stack",
      "feature": "tabm_prediction",
      "fit_rows": 1314351,
      "fold": "rw_04",
      "value": 0.027803370030824903
    },
    {
      "alpha": 1000.0,
      "component": "strong_oof_ridge_stack",
      "feature": "tree_prediction",
      "fit_rows": 1314351,
      "fold": "rw_04",
      "value": 0.14816459798753545
    },
    {
      "alpha": 1000.0,
      "component": "strong_oof_ridge_stack",
      "feature": "xgboost_prediction",
      "fit_rows": 1314351,
      "fold": "rw_04",
      "value": 0.20383524881303844
    },
    {
      "alpha": 1000.0,
      "component": "strong_oof_ridge_stack",
      "feature": "lightgbm_prediction",
      "fit_rows": 1314351,
      "fold": "rw_04",
      "value": 0.15364768066350035
    },
    {
      "alpha": 1000.0,
      "component": "strong_oof_ridge_stack",
      "feature": "ridge_calibrated_prediction",
      "fit_rows": 1314351,
      "fold": "rw_04",
      "value": 0.022091347691429307
    },
    {
      "alpha": 1000.0,
      "component": "strong_oof_ridge_stack",
      "feature": "baseline_prediction",
      "fit_rows": 1314351,
      "fold": "rw_04",
      "value": -0.07484197698256938
    },
    {
      "alpha": 1000.0,
      "component": "strong_oof_ridge_stack",
      "feature": "conservative_rls_prediction",
      "fit_rows": 1314351,
      "fold": "rw_04",
      "value": 0.16252576676601876
    },
    {
      "alpha": 1000.0,
      "component": "strong_oof_ridge_stack",
      "feature": "aggressive_rls_prediction",
      "fit_rows": 1314351,
      "fold": "rw_04",
      "value": -0.01339264068400571
    },
    {
      "alpha": 1000.0,
      "component": "strong_oof_ridge_stack",
      "feature": "tabm_s23_aux8_tabm_prediction",
      "fit_rows": 1314351,
      "fold": "rw_04",
      "value": 0.22752551130413995
    },
    {
      "alpha": 1000.0,
      "component": "strong_oof_ridge_stack",
      "feature": "tabm_s17_tabm_prediction",
      "fit_rows": 1314351,
      "fold": "rw_04",
      "value": 0.2735376720007819
    },
    {
      "alpha": 1000.0,
      "component": "strong_oof_ridge_stack",
      "feature": "gateway_risk_conservative_rls_abs_pred_s25_prediction",
      "fit_rows": 1314351,
      "fold": "rw_04",
      "value": 0.18300298765877865
    },
    {
      "alpha": 1000.0,
      "component": "strong_oof_ridge_stack",
      "feature": "gateway_risk_conservative_rls_abs_pred_s100_prediction",
      "fit_rows": 1314351,
      "fold": "rw_04",
      "value": 0.09258791745544265
    },
    {
      "alpha": 1000.0,
      "component": "strong_oof_ridge_stack",
      "feature": "gateway_risk_aggressive_rls_abs_pred_s25_prediction",
      "fit_rows": 1314351,
      "fold": "rw_04",
      "value": 0.02910781424456376
    },
    {
      "alpha": 1000.0,
      "component": "strong_oof_ridge_stack",
      "feature": "gateway_risk_aggressive_rls_abs_pred_s100_prediction",
      "fit_rows": 1314351,
      "fold": "rw_04",
      "value": 0.02020697767840169
    },
    {
      "alpha": 1000.0,
      "component": "strong_oof_ridge_stack",
      "feature": "tabm_prediction",
      "fit_rows": 1758469,
      "fold": "rw_05",
      "value": 0.08600594781030192
    },
    {
      "alpha": 1000.0,
      "component": "strong_oof_ridge_stack",
      "feature": "tree_prediction",
      "fit_rows": 1758469,
      "fold": "rw_05",
      "value": 0.16896088226981024
    },
    {
      "alpha": 1000.0,
      "component": "strong_oof_ridge_stack",
      "feature": "xgboost_prediction",
      "fit_rows": 1758469,
      "fold": "rw_05",
      "value": 0.18414035670897408
    },
    {
      "alpha": 1000.0,
      "component": "strong_oof_ridge_stack",
      "feature": "lightgbm_prediction",
      "fit_rows": 1758469,
      "fold": "rw_05",
      "value": 0.14591643962129222
    },
    {
      "alpha": 1000.0,
      "component": "strong_oof_ridge_stack",
      "feature": "ridge_calibrated_prediction",
      "fit_rows": 1758469,
      "fold": "rw_05",
      "value": 0.005216173881423824
    },
    {
      "alpha": 1000.0,
      "component": "strong_oof_ridge_stack",
      "feature": "baseline_prediction",
      "fit_rows": 1758469,
      "fold": "rw_05",
      "value": -0.026704617239296968
    },
    {
      "alpha": 1000.0,
      "component": "strong_oof_ridge_stack",
      "feature": "conservative_rls_prediction",
      "fit_rows": 1758469,
      "fold": "rw_05",
      "value": 0.19913907233152153
    },
    {
      "alpha": 1000.0,
      "component": "strong_oof_ridge_stack",
      "feature": "aggressive_rls_prediction",
      "fit_rows": 1758469,
      "fold": "rw_05",
      "value": -0.04655283661931196
    },
    {
      "alpha": 1000.0,
      "component": "strong_oof_ridge_stack",
      "feature": "tabm_s23_aux8_tabm_prediction",
      "fit_rows": 1758469,
      "fold": "rw_05",
      "value": 0.24164065964835363
    },
    {
      "alpha": 1000.0,
      "component": "strong_oof_ridge_stack",
      "feature": "tabm_s17_tabm_prediction",
      "fit_rows": 1758469,
      "fold": "rw_05",
      "value": 0.21040019743306346
    },
    {
      "alpha": 1000.0,
      "component": "strong_oof_ridge_stack",
      "feature": "gateway_risk_conservative_rls_abs_pred_s25_prediction",
      "fit_rows": 1758469,
      "fold": "rw_05",
      "value": 0.21031065605688304
    },
    {
      "alpha": 1000.0,
      "component": "strong_oof_ridge_stack",
      "feature": "gateway_risk_conservative_rls_abs_pred_s100_prediction",
      "fit_rows": 1758469,
      "fold": "rw_05",
      "value": 0.07992242106509853
    },
    {
      "alpha": 1000.0,
      "component": "strong_oof_ridge_stack",
      "feature": "gateway_risk_aggressive_rls_abs_pred_s25_prediction",
      "fit_rows": 1758469,
      "fold": "rw_05",
      "value": -0.010544016113012733
    },
    {
      "alpha": 1000.0,
      "component": "strong_oof_ridge_stack",
      "feature": "gateway_risk_aggressive_rls_abs_pred_s100_prediction",
      "fit_rows": 1758469,
      "fold": "rw_05",
      "value": -0.041165157053677986
    }
  ],
  "group_1": [],
  "group_2": [],
  "group_3": [],
  "group_4": [],
  "group_5": [
    {
      "column": "fixed_blend_0_w0p75_fixed_blend_prediction",
      "component": "fixed_blend",
      "left": "strong_oof_ridge_stack_prediction",
      "left_weight": 0.75,
      "right": "gateway_risk_conservative_rls_abs_pred_s100_prediction",
      "right_weight": 0.25
    }
  ],
  "group_6": [],
  "group_7": [],
  "group_8": [],
  "group_9": []
}
